<?xml version='1.0' encoding='utf-8'?>
<TextureAtlas imagePath="generic.png">
<SubTexture name="generic b0000" x="350" y="82" width="82" height="82" frameX="-9" frameY="-9" frameWidth="100" frameHeight="100" />
<SubTexture name="generic dpad0000" x="0" y="0" width="92" height="92" frameX="-4" frameY="-4" frameWidth="100" frameHeight="100" />
<SubTexture name="generic dpadDown0000" x="92" y="0" width="92" height="92" frameX="-4" frameY="-4" frameWidth="100" frameHeight="100" />
<SubTexture name="generic dpadLeft0000" x="0" y="92" width="92" height="92" frameX="-4" frameY="-4" frameWidth="100" frameHeight="100" />
<SubTexture name="generic dpadRight0000" x="92" y="92" width="92" height="92" frameX="-4" frameY="-4" frameWidth="100" frameHeight="100" />
<SubTexture name="generic dpadUp0000" x="184" y="0" width="92" height="92" frameX="-4" frameY="-4" frameWidth="100" frameHeight="100" />
<SubTexture name="generic lb0000" x="238" y="273" width="90" height="63" frameX="-5" frameY="-18" frameWidth="100" frameHeight="100" />
<SubTexture name="generic lStick0000" x="184" y="92" width="90" height="89" frameX="-5" frameY="-6" frameWidth="100" frameHeight="100" />
<SubTexture name="generic lStickClick0000" x="0" y="184" width="86" height="89" frameX="-7" frameY="-6" frameWidth="100" frameHeight="100" />
<SubTexture name="generic lt0000" x="276" y="0" width="74" height="85" frameX="-13" frameY="-9" frameWidth="100" frameHeight="100" />
<SubTexture name="generic rb0000" x="328" y="273" width="90" height="63" frameX="-5" frameY="-18" frameWidth="100" frameHeight="100" />
<SubTexture name="generic rStick0000" x="86" y="184" width="90" height="89" frameX="-5" frameY="-6" frameWidth="100" frameHeight="100" />
<SubTexture name="generic rStickClick0000" x="176" y="184" width="86" height="89" frameX="-7" frameY="-6" frameWidth="100" frameHeight="100" />
<SubTexture name="generic rt0000" x="276" y="85" width="74" height="85" frameX="-13" frameY="-9" frameWidth="100" frameHeight="100" />
<SubTexture name="generic x0000" x="350" y="164" width="82" height="82" frameX="-9" frameY="-9" frameWidth="100" frameHeight="100" />
<SubTexture name="generic y0000" x="0" y="273" width="82" height="82" frameX="-9" frameY="-9" frameWidth="100" frameHeight="100" />
<SubTexture name="generic menu0000" x="82" y="273" width="78" height="77" frameX="-11" frameY="-12" frameWidth="100" frameHeight="100" />
<SubTexture name="generic windows0000" x="160" y="273" width="78" height="77" frameX="-11" frameY="-12" frameWidth="100" frameHeight="100" />
<SubTexture name="generic a0000" x="350" y="0" width="82" height="82" frameX="-9" frameY="-9" frameWidth="100" frameHeight="100" />
</TextureAtlas>
